.DS_Store
buildings_bench/__init__.py
buildings_bench/tokenizer.py
buildings_bench/transforms.py
buildings_bench/utils.py
buildings_bench/configs/AveragePersistence.toml
buildings_bench/configs/CopyLastDayPersistence.toml
buildings_bench/configs/CopyLastWeekPersistence.toml
buildings_bench/configs/DLinearRegression.toml
buildings_bench/configs/DeepAutoregressiveRNN.toml
buildings_bench/configs/LinearRegression.toml
buildings_bench/configs/TransformerWithGaussian-L.toml
buildings_bench/configs/TransformerWithGaussian-M.toml
buildings_bench/configs/TransformerWithGaussian-S.toml
buildings_bench/configs/TransformerWithGaussian-t-L.toml
buildings_bench/configs/TransformerWithGaussian-t-M.toml
buildings_bench/configs/TransformerWithGaussian-t-S.toml
buildings_bench/configs/TransformerWithGaussian-th-L.toml
buildings_bench/configs/TransformerWithGaussian-th-M.toml
buildings_bench/configs/TransformerWithGaussian-th-S.toml
buildings_bench/configs/TransformerWithGaussian-weather-L.toml
buildings_bench/configs/TransformerWithGaussian-weather-M.toml
buildings_bench/configs/TransformerWithGaussian-weather-S.toml
buildings_bench/configs/TransformerWithMSE.toml
buildings_bench/configs/TransformerWithTokenizer-L-344.toml
buildings_bench/configs/TransformerWithTokenizer-L-474.toml
buildings_bench/configs/TransformerWithTokenizer-L-8192.toml
buildings_bench/configs/TransformerWithTokenizer-L-ignore-spatial.toml
buildings_bench/configs/TransformerWithTokenizer-L.toml
buildings_bench/configs/TransformerWithTokenizer-M.toml
buildings_bench/configs/TransformerWithTokenizer-S.toml
buildings_bench/data/__init__.py
buildings_bench/data/buildings900K.py
buildings_bench/data/datasets.py
buildings_bench/evaluation/__init__.py
buildings_bench/evaluation/aggregate.py
buildings_bench/evaluation/managers.py
buildings_bench/evaluation/metrics.py
buildings_bench/evaluation/scoring_rules.py
buildings_bench/models/__init__.py
buildings_bench/models/base_model.py
buildings_bench/models/deep_rnn.py
buildings_bench-2.0.0.dist-info/LICENSE
buildings_bench-2.0.0.dist-info/METADATA
buildings_bench-2.0.0.dist-info/WHEEL
buildings_bench-2.0.0.dist-info/top_level.txt
buildings_bench-2.0.0.dist-info/RECORD
