Metadata-Version: 2.1
Name: buildings-bench
Version: 2.0.0
Summary: Large-scale pretraining and benchmarking for short-term load forecasting.
Home-page: https://nrel.github.io/BuildingsBench/
Author: Patrick Emami
Author-email: Patrick.Emami@nrel.gov
License: BSD 3-Clause
Keywords: forecasting,energy,buildings,benchmark
Classifier: Development Status :: 3 - Alpha
Classifier: Intended Audience :: Science/Research
Classifier: License :: OSI Approved :: BSD License
Classifier: Natural Language :: English
Classifier: Programming Language :: Python :: 3
Classifier: Topic :: Scientific/Engineering :: Artificial Intelligence
Requires-Python: >=3.8
License-File: LICENSE
Requires-Dist: torch (==2.4.1)
Requires-Dist: pandas (>=2.0.0)
Requires-Dist: pyarrow
Requires-Dist: tomli
Requires-Dist: scikit-learn (==1.1.3)
Requires-Dist: tqdm
Requires-Dist: rliable
Requires-Dist: transformers (==4.34.0)
Provides-Extra: benchmark
Requires-Dist: wandb ; extra == 'benchmark'
Requires-Dist: properscoring ; extra == 'benchmark'
Requires-Dist: matplotlib ; extra == 'benchmark'
Requires-Dist: seaborn ; extra == 'benchmark'
Requires-Dist: jupyterlab ; extra == 'benchmark'
